Workbook
Name SegmentaçãodeDados_MÊS: #N/A

Sheet RELATORIO
B2: MÊS | C2: JAN | E2: Não edite nada aqui
B3: ANO | C3: 2026
B5: RECEITAS | E5: DESPESAS
B6: SALARIO | C6: =SUMIFS('REGISTROS DIARIOS'!G:G,'REGISTROS DIARIOS'!C:C,RELATORIO!$C$2,'REGISTROS DIARIOS'!F:F,RELATORIO!$B$6,'REGISTROS DIARIOS'!E:E,RELATORIO!$B$5) -> 1500 | E6: FIXAS | F6: =SUMIFS('REGISTROS DIARIOS'!$G:$G,'REGISTROS DIARIOS'!C:C,RELATORIO!$C$2,'REGISTROS DIARIOS'!E:E,RELATORIO!$E$5,'REGISTROS DIARIOS'!F:F,RELATORIO!$E$6) -> 0
B7: EXTRAS | C7: =SUMIFS('REGISTROS DIARIOS'!G:G,'REGISTROS DIARIOS'!C:C,RELATORIO!C2,'REGISTROS DIARIOS'!F:F,RELATORIO!$B$7,'REGISTROS DIARIOS'!E:E,RELATORIO!$B$5) -> 0 | E7: VARIAVEIS | F7: =SUMIFS('REGISTROS DIARIOS'!$G:$G,'REGISTROS DIARIOS'!$C:$C,RELATORIO!$C$2,'REGISTROS DIARIOS'!$E:$E,"DESPESAS",'REGISTROS DIARIOS'!$F:$F,RELATORIO!$E7) -> 0
B8: OUTRAS R | C8: =SUMIFS('REGISTROS DIARIOS'!G:G,'REGISTROS DIARIOS'!C:C,RELATORIO!$C$2,'REGISTROS DIARIOS'!F:F,RELATORIO!$B$8,'REGISTROS DIARIOS'!E:E,RELATORIO!$B$5) -> 0 | E8: OUTRAS D | F8: =SUMIFS('REGISTROS DIARIOS'!$G:$G,'REGISTROS DIARIOS'!$C:$C,RELATORIO!$C$2,'REGISTROS DIARIOS'!$E:$E,"DESPESAS",'REGISTROS DIARIOS'!$F:$F,RELATORIO!$E8) -> 0
B9: TOTAL | C9: =SUM(C6:C8) -> 1500 | E9: TOTAL | F9: =SUM(F6:F8) -> 0
B12: STATUS ATUAL | D12: =$C$9-$F$9 -> 1500
D18: ACOMPANHAMENTO MENSAL
C20: JAN | D20: FEV | E20: MAR | F20: ABR | G20: MAI | H20: JUN | I20: JUL | J20: AGO | K20: SET | L20: OUT | M20: NOV | N20: DEZ
B21: RECEITAS | C21: =SUMIFS('REGISTROS DIARIOS'!$G:$G,'REGISTROS DIARIOS'!$C:$C,RELATORIO!C$20,'REGISTROS DIARIOS'!$D:$D,RELATORIO!$C$3,'REGISTROS DIARIOS'!$E:$E,RELATORIO!$B21) -> 1500 | D21: =SUMIFS('REGISTROS DIARIOS'!$G:$G,'REGISTROS DIARIOS'!$C:$C,RELATORIO!D$20,'REGISTROS DIARIOS'!$D:$D,RELATORIO!$C$3,'REGISTROS DIARIOS'!$E:$E,RELATORIO!$B21) -> 0 | E21: =SUMIFS('REGISTROS DIARIOS'!$G:$G,'REGISTROS DIARIOS'!$C:$C,RELATORIO!E$20,'REGISTROS DIARIOS'!$D:$D,RELATORIO!$C$3,'REGISTROS DIARIOS'!$E:$E,RELATORIO!$B21) -> 0 | F21: =SUMIFS('REGISTROS DIARIOS'!$G:$G,'REGISTROS DIARIOS'!$C:$C,RELATORIO!F$20,'REGISTROS DIARIOS'!$D:$D,RELATORIO!$C$3,'REGISTROS DIARIOS'!$E:$E,RELATORIO!$B21) -> 0 | G21: =SUMIFS('REGISTROS DIARIOS'!$G:$G,'REGISTROS DIARIOS'!$C:$C,RELATORIO!G$20,'REGISTROS DIARIOS'!$D:$D,RELATORIO!$C$3,'REGISTROS DIARIOS'!$E:$E,RELATORIO!$B21) -> 0 | H21: =SUMIFS('REGISTROS DIARIOS'!$G:$G,'REGISTROS DIARIOS'!$C:$C,RELATORIO!H$20,'REGISTROS DIARIOS'!$D:$D,RELATORIO!$C$3,'REGISTROS DIARIOS'!$E:$E,RELATORIO!$B21) -> 0 | I21: =SUMIFS('REGISTROS DIARIOS'!$G:$G,'REGISTROS DIARIOS'!$C:$C,RELATORIO!I$20,'REGISTROS DIARIOS'!$D:$D,RELATORIO!$C$3,'REGISTROS DIARIOS'!$E:$E,RELATORIO!$B21) -> 0 | J21: =SUMIFS('REGISTROS DIARIOS'!$G:$G,'REGISTROS DIARIOS'!$C:$C,RELATORIO!J$20,'REGISTROS DIARIOS'!$D:$D,RELATORIO!$C$3,'REGISTROS DIARIOS'!$E:$E,RELATORIO!$B21) -> 0 | ... N21: =SUMIFS('REGISTROS DIARIOS'!$G:$G,'REGISTROS DIARIOS'!$C:$C,RELATORIO!N$20,'REGISTROS DIARIOS'!$D:$D,RELATORIO!$C$3,'REGISTROS DIARIOS'!$E:$E,RELATORIO!$B21) -> 0
B22: DESPESAS | C22: =SUMIFS('REGISTROS DIARIOS'!$G:$G,'REGISTROS DIARIOS'!$C:$C,RELATORIO!C$20,'REGISTROS DIARIOS'!$D:$D,RELATORIO!$C$3,'REGISTROS DIARIOS'!$E:$E,RELATORIO!$B22) -> 0 | D22: =SUMIFS('REGISTROS DIARIOS'!$G:$G,'REGISTROS DIARIOS'!$C:$C,RELATORIO!D$20,'REGISTROS DIARIOS'!$D:$D,RELATORIO!$C$3,'REGISTROS DIARIOS'!$E:$E,RELATORIO!$B22) -> 0 | E22: =SUMIFS('REGISTROS DIARIOS'!$G:$G,'REGISTROS DIARIOS'!$C:$C,RELATORIO!E$20,'REGISTROS DIARIOS'!$D:$D,RELATORIO!$C$3,'REGISTROS DIARIOS'!$E:$E,RELATORIO!$B22) -> 0 | F22: =SUMIFS('REGISTROS DIARIOS'!$G:$G,'REGISTROS DIARIOS'!$C:$C,RELATORIO!F$20,'REGISTROS DIARIOS'!$D:$D,RELATORIO!$C$3,'REGISTROS DIARIOS'!$E:$E,RELATORIO!$B22) -> 0 | G22: =SUMIFS('REGISTROS DIARIOS'!$G:$G,'REGISTROS DIARIOS'!$C:$C,RELATORIO!G$20,'REGISTROS DIARIOS'!$D:$D,RELATORIO!$C$3,'REGISTROS DIARIOS'!$E:$E,RELATORIO!$B22) -> 0 | H22: =SUMIFS('REGISTROS DIARIOS'!$G:$G,'REGISTROS DIARIOS'!$C:$C,RELATORIO!H$20,'REGISTROS DIARIOS'!$D:$D,RELATORIO!$C$3,'REGISTROS DIARIOS'!$E:$E,RELATORIO!$B22) -> 0 | I22: =SUMIFS('REGISTROS DIARIOS'!$G:$G,'REGISTROS DIARIOS'!$C:$C,RELATORIO!I$20,'REGISTROS DIARIOS'!$D:$D,RELATORIO!$C$3,'REGISTROS DIARIOS'!$E:$E,RELATORIO!$B22) -> 0 | J22: =SUMIFS('REGISTROS DIARIOS'!$G:$G,'REGISTROS DIARIOS'!$C:$C,RELATORIO!J$20,'REGISTROS DIARIOS'!$D:$D,RELATORIO!$C$3,'REGISTROS DIARIOS'!$E:$E,RELATORIO!$B22) -> 0 | ... N22: =SUMIFS('REGISTROS DIARIOS'!$G:$G,'REGISTROS DIARIOS'!$C:$C,RELATORIO!N$20,'REGISTROS DIARIOS'!$D:$D,RELATORIO!$C$3,'REGISTROS DIARIOS'!$E:$E,RELATORIO!$B22) -> 0
B23: SALDO MÊS | C23: =C21-C22 -> 1500 | D23: =D21-D22 -> 0 | E23: =E21-E22 -> 0 | F23: =F21-F22 -> 0 | G23: =G21-G22 -> 0 | H23: =H21-H22 -> 0 | I23: =I21-I22 -> 0 | J23: =J21-J22 -> 0 | ... N23: =N21-N22 -> 0
B24: SOMA SALDO | C24: =SUM(C23,B24) -> 1500 | D24: =SUM(D23,C24) -> 1500 | E24: =SUM(E23,D24) -> 1500 | F24: =SUM(F23,E24) -> 1500 | G24: =SUM(G23,F24) -> 1500 | H24: =SUM(H23,G24) -> 1500 | I24: =SUM(I23,H24) -> 1500 | J24: =SUM(J23,I24) -> 1500 | ... N24: =SUM(N23,M24) -> 1500

Sheet REGISTROS DIARIOS
C2: FAÇA AQUI SEUS LANÇAMENTOS DIÁRIOS
B6: DATA | C6: MÊS | D6: ANO | E6: ORIGEM | F6: DESCRIÇÃO | G6: VALOR | H6: DETALHES | I6: OBSERVAÇÂO
B7: 46023 | C7: =TEXT(B7,"MMM") -> jan | D7: =TEXT(B7,"AAA") -> 2026 | E7: RECEITAS | F7: SALARIO | G7: 1500 | H7: Em dinheiro | I7: ...

Sheet DADOS
B2: Origens | D2: Descrição | F2: Meses
B3: RECEITAS | D3: SALARIO | F3: JAN
B4: DESPESAS | D4: EXTRAS | F4: FEV
D5: FIXAS | F5: MAR
D6: VARIAVEIS | F6: ABR
D7: OUTRAS R | F7: MAI
D8: OUTRAS D | F8: JUN
F9: JUL
F10: AGO
F11: SET
F12: OUT
F13: NOV
F14: DEZ
